mcphawk/__init__.py
mcphawk/cli.py
mcphawk/logger.py
mcphawk/models.py
mcphawk/sniffer.py
mcphawk/stdio_server_detector_fallback.py
mcphawk/tcp_reassembly.py
mcphawk/transport_detector.py
mcphawk/utils.py
mcphawk/wrapper.py
mcphawk/mcp_server/__init__.py
mcphawk/mcp_server/server.py
mcphawk/web/__init__.py
mcphawk/web/broadcaster.py
mcphawk/web/server.py
mcphawk/web/static/index.html
mcphawk/web/static/mcphawk_logo.png
mcphawk/web/static/assets/index-DC4K23Wn.js
mcphawk/web/static/assets/index-Do4cWYV7.css
mcphawk/web/static/assets/ui-CZuBMD6M.js
mcphawk/web/static/assets/vendor-CmqOmjtB.js
mcphawk-0.4.3.dist-info/licenses/LICENSE
mcphawk-0.4.3.dist-info/METADATA
mcphawk-0.4.3.dist-info/WHEEL
mcphawk-0.4.3.dist-info/entry_points.txt
mcphawk-0.4.3.dist-info/top_level.txt
mcphawk-0.4.3.dist-info/RECORD
