Metadata-Version: 2.4
Name: mcphawk
Version: 0.4.3
Summary: MCPHawk is a Logging & Monitoring solution for MCP traffic, providing deep visibility into MCP client-server interactions
Author: tech4242
License: MIT License
Project-URL: Homepage, https://github.com/tech4242/mcphawk
Project-URL: Bug Tracker, https://github.com/tech4242/mcphawk/issues
Requires-Python: >=3.10
License-File: LICENSE
Requires-Dist: scapy>=2.5.0
Requires-Dist: psutil>=6.0.0
Requires-Dist: typer>=0.12.0
Requires-Dist: fastapi>=0.116.1
Requires-Dist: uvicorn[standard]>=0.35.0
Requires-Dist: mcp>=1.0.0
Requires-Dist: websockets>=12.0
Dynamic: license-file
